{
    "data": [
        {
            "nightstand_frame": ""
        },
        {
            "nightstand_frame": "<Drawer_Back><Board>[<FrontFace>]",
            "nightstand_drawer": ""
        },
        {
            "nightstand_frame": "<Wireless_Charging_Pad><Block>[<BottomFace>]",
            "charging_station": ""
        },
        {
            "left_side_panel": "<Left_Side_Panel><Board>[<TopFace>]",
            "top_panel": ""
        },
        {
            "right_side_panel": "<Right_Side_Panel><Board>[<TopFace>]",
            "top_panel": ""
        },
        {
            "shelf_panel": "<Shelf_Panel><Board>[<LeftFace>]",
            "left_side_panel": ""
        },
        {
            "shelf_panel": "<Shelf_Panel><Board>[<RightFace>]",
            "right_side_panel": ""
        },
        {
            "left_side_panel": "<Left_Side_Panel><Board>[<BottomFace>]",
            "bottom_panel": ""
        },
        {
            "right_side_panel": "<Right_Side_Panel><Board>[<BottomFace>]",
            "bottom_panel": ""
        },
        {
            "bottom_panel": "<Bottom_Panel><Board>[<TopFace>]",
            "shelf_panel": ""
        },
        {
            "back_panel": ""
        },
        {
            "wireless_charging_pad": "<Wireless_Charging_Pad><Block>[<LeftFace>]",
            "usb_ports": ""
        }
    ],
    "meta_data": [
        {
            "row_headers": [
                "Component",
                "Nightstand_Frame",
                "Nightstand_Drawer",
                "Charging_Station"
            ],
            "column_header": [
                "Nightstand_Frame",
                "Nightstand_Drawer",
                "Charging_Station",
                "Charging_Station",
                "Nightstand_Frame",
                "Nightstand_Frame",
                "Nightstand_Frame",
                "Nightstand_Drawer"
            ],
            "title": "table_1",
            "data": [
                {
                    "nightstand_frame": ""
                },
                {
                    "nightstand_frame": "<Drawer_Back><Board>[<FrontFace>]",
                    "nightstand_drawer": ""
                },
                {
                    "nightstand_frame": "<Wireless_Charging_Pad><Block>[<BottomFace>]",
                    "charging_station": ""
                }
            ]
        },
        {
            "row_headers": [
                "Component",
                "Top_Panel",
                "Left_Side_Panel",
                "Right_Side_Panel",
                "Bottom_Panel",
                "Shelf_Panel",
                "Back_Panel"
            ],
            "column_header": [
                "Top_Panel",
                "Left_Side_Panel",
                "Right_Side_Panel",
                "Bottom_Panel",
                "Shelf_Panel",
                "Back_Panel",
                "Top_Panel",
                "Bottom_Panel",
                "Back_Panel",
                "Left_Side_Panel",
                "Right_Side_Panel",
                "Shelf_Panel",
                "Back_Panel",
                "Left_Side_Panel",
                "Right_Side_Panel",
                "Back_Panel",
                "Back_Panel"
            ],
            "title": "table_2",
            "data": [
                {
                    "left_side_panel": "<Left_Side_Panel><Board>[<TopFace>]",
                    "top_panel": ""
                },
                {
                    "right_side_panel": "<Right_Side_Panel><Board>[<TopFace>]",
                    "top_panel": ""
                },
                {
                    "shelf_panel": "<Shelf_Panel><Board>[<LeftFace>]",
                    "left_side_panel": ""
                },
                {
                    "shelf_panel": "<Shelf_Panel><Board>[<RightFace>]",
                    "right_side_panel": ""
                },
                {
                    "left_side_panel": "<Left_Side_Panel><Board>[<BottomFace>]",
                    "bottom_panel": ""
                },
                {
                    "right_side_panel": "<Right_Side_Panel><Board>[<BottomFace>]",
                    "bottom_panel": ""
                },
                {
                    "bottom_panel": "<Bottom_Panel><Board>[<TopFace>]",
                    "shelf_panel": ""
                },
                {
                    "back_panel": ""
                }
            ]
        },
        {
            "row_headers": [
                "Component",
                "Drawer_Front",
                "Drawer_Back",
                "Drawer_Left",
                "Drawer_Right",
                "Drawer_Bottom"
            ],
            "column_header": [
                "Drawer_Front",
                "Drawer_Back",
                "Drawer_Left",
                "Drawer_Right",
                "Drawer_Bottom",
                "Drawer_Back",
                "Drawer_Left",
                "Drawer_Right",
                "Drawer_Bottom",
                "Drawer_Left",
                "Drawer_Right",
                "Drawer_Bottom",
                "Drawer_Right",
                "Drawer_Bottom",
                "Drawer_Bottom"
            ],
            "title": "table_3",
            "data": []
        },
        {
            "row_headers": [
                "Component",
                "USB_Ports",
                "Wireless_Charging_Pad"
            ],
            "column_header": [
                "USB_Ports",
                "Wireless_Charging_Pad",
                "USB_Ports",
                "Wireless_Charging_Pad"
            ],
            "title": "table_4",
            "data": [
                {
                    "wireless_charging_pad": "<Wireless_Charging_Pad><Block>[<LeftFace>]",
                    "usb_ports": ""
                }
            ]
        }
    ]
}